{"_id":{"$oid":"626e91d01093e204f9ab4c46"},"key":"shanghai","name":"上海","status":1,"createTime":{"$date":"2022-05-01T13:57:36.731Z"},"modifyTime":{"$date":"2022-05-14T15:30:13.733Z"},"order":2}
{"_id":{"$oid":"626e91d01093e204f9ab4c47"},"key":"beijing","name":"北京","status":1,"createTime":{"$date":"2022-05-01T13:57:36.731Z"},"modifyTime":{"$date":"2022-05-27T10:42:00.008Z"},"order":10}
{"_id":{"$oid":"627fcb1c5b34264d00204f11"},"createTime":{"$date":"2022-05-14T15:22:29.896Z"},"modifyTime":{"$date":"2022-05-14T15:22:29.896Z"},"createId":1,"modifyId":1,"isDelete":false,"order":1,"status":1,"desc":"","remark":"","key":"hh","name":"哈哈","__v":0}
{"_id":{"$oid":"628337b2bfd377cabc8131d2"},"createTime":{"$date":"2022-05-16T12:30:17.535Z"},"modifyTime":{"$date":"2022-05-16T12:30:17.535Z"},"createId":1,"modifyId":1,"isDelete":false,"order":1,"status":1,"desc":"","remark":"","key":"chengdu","name":"成都","__v":0}
