{"_id":{"$oid":"627f65e0423956260e32fd91"},"key":"practice","name":"岗前实习","status":1.0,"createTime":{"$date":"2022-05-14T08:18:40.356Z"},"modifyTime":{"$date":"2022-05-14T08:18:40.356Z"}}
{"_id":{"$oid":"627f65e0423956260e32fd92"},"key":"school","name":"校园招聘2","status":1.0,"createTime":{"$date":"2022-05-14T08:18:40.356Z"},"modifyTime":{"$date":"2022-05-14T08:18:40.356Z"}}
{"_id":{"$oid":"627f65e0423956260e32fd93"},"key":"society","name":"社会招聘1","status":1.0,"createTime":{"$date":"2022-05-14T08:18:40.356Z"},"modifyTime":{"$date":"2022-05-14T08:18:40.356Z"}}
